teslagenerator_ok/__init__.py
teslagenerator_ok/crawler.py
teslagenerator_ok/faker.py
teslagenerator_ok/data/__init__.py
teslagenerator_ok/data/english/__init__.py
teslagenerator_ok/data/english/all.txt
teslagenerator_ok/data/english/boy.txt
teslagenerator_ok/data/english/firstnames.txt
teslagenerator_ok/data/english/girl.txt
teslagenerator_ok/data/vietnamese/__init__.py
teslagenerator_ok/data/vietnamese/all.txt
teslagenerator_ok/data/vietnamese/boy.txt
teslagenerator_ok/data/vietnamese/firstname.txt
teslagenerator_ok/data/vietnamese/firstnames.txt
teslagenerator_ok/data/vietnamese/fullname.json
teslagenerator_ok/data/vietnamese/girl.txt
teslagenerator_ok/data/vietnamese/girl_one_word.txt
teslagenerator_ok/data/vietnamese/girl_one_word_unsigned.txt
teslagenerator_ok/data/vietnamese/girl_unsigned.txt
teslagenerator_ok-0.0.5.dist-info/METADATA
teslagenerator_ok-0.0.5.dist-info/WHEEL
teslagenerator_ok-0.0.5.dist-info/top_level.txt
teslagenerator_ok-0.0.5.dist-info/RECORD
